{
  "updated": "2026-04-16T15:36:27.448723+08:00",
  "sectors": [
    {
      "name": "专精特新",
      "netAmount": 14082033256.82,
      "avgChange": 2.11,
      "leader": {
        "code": "sz301148",
        "name": "嘉戎技术",
        "change": 20.0
      },
      "hotStocks": [
        {
          "code": "sz300394",
          "name": "天孚通信",
          "change": 7.53,
          "netAmount": 3774232250.54,
          "reason": "强势拉升+净流入37.7亿"
        },
        {
          "code": "sh600105",
          "name": "永鼎股份",
          "change": 5.14,
          "netAmount": 835325436.09,
          "reason": "显著上涨+净流入8.4亿"
        },
        {
          "code": "sz300604",
          "name": "长川科技",
          "change": 9.12,
          "netAmount": 778075131.5,
          "reason": "强势拉升+净流入7.8亿"
        },
        {
          "code": "sz300290",
          "name": "荣科科技",
          "change": 15.02,
          "netAmount": 394296578.24,
          "reason": "涨停+净流入3.9亿"
        },
        {
          "code": "sz002757",
          "name": "南兴股份",
          "change": 9.99,
          "netAmount": 379222213.04,
          "reason": "涨停+净流入3.8亿"
        }
      ]
    },
    {
      "name": "锂电池",
      "netAmount": 13209157113.93,
      "avgChange": 2.24,
      "leader": {
        "code": "sz000571",
        "name": "新大洲A",
        "change": 10.06
      },
      "hotStocks": [
        {
          "code": "sh600549",
          "name": "厦门钨业",
          "change": 10.01,
          "netAmount": 2299858506.52,
          "reason": "涨停+净流入23.0亿"
        },
        {
          "code": "sz002263",
          "name": "大东南",
          "change": 10.0,
          "netAmount": 1385600826.68,
          "reason": "涨停+净流入13.9亿"
        },
        {
          "code": "sz002491",
          "name": "通鼎互联",
          "change": 10.0,
          "netAmount": 1238526981.8,
          "reason": "涨停+净流入12.4亿"
        },
        {
          "code": "sz002594",
          "name": "比亚迪",
          "change": 2.44,
          "netAmount": 1014111780.01,
          "reason": "净流入10.1亿"
        },
        {
          "code": "sz002240",
          "name": "盛新锂能",
          "change": 7.63,
          "netAmount": 873799418.9,
          "reason": "强势拉升+净流入8.7亿"
        }
      ]
    },
    {
      "name": "股权激励",
      "netAmount": 13155694835.35,
      "avgChange": 1.2,
      "leader": {
        "code": "sz300027",
        "name": "华谊兄弟",
        "change": 20.11
      },
      "hotStocks": [
        {
          "code": "sz002008",
          "name": "大族激光",
          "change": 10.0,
          "netAmount": 1414181238.95,
          "reason": "涨停+净流入14.1亿"
        },
        {
          "code": "sz002491",
          "name": "通鼎互联",
          "change": 10.0,
          "netAmount": 1238526981.8,
          "reason": "涨停+净流入12.4亿"
        },
        {
          "code": "sz300058",
          "name": "蓝色光标",
          "change": 4.69,
          "netAmount": 1097643835.28,
          "reason": "显著上涨+净流入11.0亿"
        },
        {
          "code": "sz300017",
          "name": "网宿科技",
          "change": 4.82,
          "netAmount": 745962547.3,
          "reason": "显著上涨+净流入7.5亿"
        },
        {
          "code": "sz002213",
          "name": "大为股份",
          "change": 10.01,
          "netAmount": 742562205.66,
          "reason": "涨停+净流入7.4亿"
        }
      ]
    },
    {
      "name": "光伏",
      "netAmount": 12282428071.02,
      "avgChange": 1.26,
      "leader": {
        "code": "sz300738",
        "name": "奥飞数据",
        "change": 10.86
      },
      "hotStocks": [
        {
          "code": "sz002008",
          "name": "大族激光",
          "change": 10.0,
          "netAmount": 1414181238.95,
          "reason": "涨停+净流入14.1亿"
        },
        {
          "code": "sh601778",
          "name": "晶科科技",
          "change": 10.08,
          "netAmount": 1410486179.82,
          "reason": "涨停+净流入14.1亿"
        },
        {
          "code": "sz002263",
          "name": "大东南",
          "change": 10.0,
          "netAmount": 1385600826.68,
          "reason": "涨停+净流入13.9亿"
        },
        {
          "code": "sz300738",
          "name": "奥飞数据",
          "change": 10.86,
          "netAmount": 1007556832.9,
          "reason": "涨停+净流入10.1亿"
        },
        {
          "code": "sz002929",
          "name": "润建股份",
          "change": 10.01,
          "netAmount": 356879388.28,
          "reason": "涨停+净流入3.6亿"
        }
      ]
    },
    {
      "name": "重组概念",
      "netAmount": 12034925638.37,
      "avgChange": 1.29,
      "leader": {
        "code": "sz300351",
        "name": "永贵电器",
        "change": 11.56
      },
      "hotStocks": [
        {
          "code": "sh600666",
          "name": "奥瑞德",
          "change": 9.95,
          "netAmount": 1538916256.75,
          "reason": "涨停+净流入15.4亿"
        },
        {
          "code": "sz002468",
          "name": "申通快递",
          "change": 10.01,
          "netAmount": 935669669.72,
          "reason": "涨停+净流入9.4亿"
        },
        {
          "code": "sz300322",
          "name": "硕贝德",
          "change": 7.79,
          "netAmount": 914579584.31,
          "reason": "强势拉升+净流入9.1亿"
        },
        {
          "code": "sz002297",
          "name": "博云新材",
          "change": 9.99,
          "netAmount": 783793766.59,
          "reason": "涨停+净流入7.8亿"
        },
        {
          "code": "sh600986",
          "name": "浙文互联",
          "change": 7.44,
          "netAmount": 714243347.82,
          "reason": "强势拉升+净流入7.1亿"
        }
      ]
    },
    {
      "name": "锂矿",
      "netAmount": 11007810747.87,
      "avgChange": 2.91,
      "leader": {
        "code": "sz300587",
        "name": "天铁科技",
        "change": 14.04
      },
      "hotStocks": [
        {
          "code": "sz300390",
          "name": "天华新能",
          "change": 11.37,
          "netAmount": 1732025951.19,
          "reason": "涨停+净流入17.3亿"
        },
        {
          "code": "sz002594",
          "name": "比亚迪",
          "change": 2.44,
          "netAmount": 1014111780.01,
          "reason": "净流入10.1亿"
        },
        {
          "code": "sz002240",
          "name": "盛新锂能",
          "change": 7.63,
          "netAmount": 873799418.9,
          "reason": "强势拉升+净流入8.7亿"
        },
        {
          "code": "sh603799",
          "name": "华友钴业",
          "change": 5.02,
          "netAmount": 843002613.85,
          "reason": "显著上涨+净流入8.4亿"
        },
        {
          "code": "sz000762",
          "name": "西藏矿业",
          "change": 9.99,
          "netAmount": 767388183.9,
          "reason": "涨停+净流入7.7亿"
        }
      ]
    },
    {
      "name": "融资融券",
      "netAmount": 10834247016.85,
      "avgChange": 0.23,
      "leader": {
        "code": "sh600549",
        "name": "厦门钨业",
        "change": 10.01
      },
      "hotStocks": [
        {
          "code": "sh600549",
          "name": "厦门钨业",
          "change": 10.01,
          "netAmount": 2299858506.52,
          "reason": "涨停+净流入23.0亿"
        },
        {
          "code": "sh600875",
          "name": "东方电气",
          "change": 9.99,
          "netAmount": 2207647031.51,
          "reason": "涨停+净流入22.1亿"
        },
        {
          "code": "sz002008",
          "name": "大族激光",
          "change": 10.0,
          "netAmount": 1414181238.95,
          "reason": "涨停+净流入14.1亿"
        },
        {
          "code": "sz000762",
          "name": "西藏矿业",
          "change": 9.99,
          "netAmount": 767388183.9,
          "reason": "涨停+净流入7.7亿"
        },
        {
          "code": "sz000792",
          "name": "盐湖股份",
          "change": 4.05,
          "netAmount": 706695309.66,
          "reason": "显著上涨+净流入7.1亿"
        }
      ]
    },
    {
      "name": "业绩预升",
      "netAmount": 10564339699.04,
      "avgChange": 1.02,
      "leader": {
        "code": "sz300027",
        "name": "华谊兄弟",
        "change": 20.11
      },
      "hotStocks": [
        {
          "code": "sz300088",
          "name": "长信科技",
          "change": 14.1,
          "netAmount": 2187566195.9,
          "reason": "涨停+净流入21.9亿"
        },
        {
          "code": "sz000070",
          "name": "特发信息",
          "change": 10.01,
          "netAmount": 1756370172.99,
          "reason": "涨停+净流入17.6亿"
        },
        {
          "code": "sz300017",
          "name": "网宿科技",
          "change": 4.82,
          "netAmount": 745962547.3,
          "reason": "显著上涨+净流入7.5亿"
        },
        {
          "code": "sz300027",
          "name": "华谊兄弟",
          "change": 20.11,
          "netAmount": 480235680.77,
          "reason": "涨停+净流入4.8亿"
        },
        {
          "code": "sz002353",
          "name": "杰瑞股份",
          "change": 6.23,
          "netAmount": 299552435.85,
          "reason": "显著上涨+净流入3.0亿"
        }
      ]
    },
    {
      "name": "稀缺资源",
      "netAmount": 7845808631.12,
      "avgChange": 2.57,
      "leader": {
        "code": "sh600549",
        "name": "厦门钨业",
        "change": 10.01
      },
      "hotStocks": [
        {
          "code": "sh600549",
          "name": "厦门钨业",
          "change": 10.01,
          "netAmount": 2299858506.52,
          "reason": "涨停+净流入23.0亿"
        },
        {
          "code": "sh603799",
          "name": "华友钴业",
          "change": 5.02,
          "netAmount": 843002613.85,
          "reason": "显著上涨+净流入8.4亿"
        },
        {
          "code": "sz000762",
          "name": "西藏矿业",
          "change": 9.99,
          "netAmount": 767388183.9,
          "reason": "涨停+净流入7.7亿"
        },
        {
          "code": "sz000792",
          "name": "盐湖股份",
          "change": 4.05,
          "netAmount": 706695309.66,
          "reason": "显著上涨+净流入7.1亿"
        },
        {
          "code": "sz002192",
          "name": "融捷股份",
          "change": 6.3,
          "netAmount": 378732852.59,
          "reason": "显著上涨+净流入3.8亿"
        }
      ]
    },
    {
      "name": "光伏概念",
      "netAmount": 7764738441.6,
      "avgChange": 1.19,
      "leader": {
        "code": "sz002613",
        "name": "北玻股份",
        "change": 10.03
      },
      "hotStocks": [
        {
          "code": "sz002008",
          "name": "大族激光",
          "change": 10.0,
          "netAmount": 1414181238.95,
          "reason": "涨停+净流入14.1亿"
        },
        {
          "code": "sz002384",
          "name": "东山精密",
          "change": 2.57,
          "netAmount": 1200425255.45,
          "reason": "净流入12.0亿"
        },
        {
          "code": "sz000815",
          "name": "美利云",
          "change": 10.01,
          "netAmount": 982103578.31,
          "reason": "涨停+净流入9.8亿"
        },
        {
          "code": "sh600673",
          "name": "东阳光",
          "change": 6.41,
          "netAmount": 420837076.77,
          "reason": "显著上涨+净流入4.2亿"
        },
        {
          "code": "sz002132",
          "name": "恒星科技",
          "change": 6.51,
          "netAmount": 336861486.43,
          "reason": "显著上涨+净流入3.4亿"
        }
      ]
    }
  ],
  "recommend": [
    {
      "code": "sz300058",
      "name": "蓝色光标",
      "sector": "股权激励",
      "score": 99,
      "reason": "[股权激励]显著上涨+净流入11.0亿",
      "suggestGroup": "watch"
    },
    {
      "code": "sh600105",
      "name": "永鼎股份",
      "sector": "专精特新",
      "score": 99,
      "reason": "[专精特新]显著上涨+净流入8.4亿",
      "suggestGroup": "watch"
    },
    {
      "code": "sz300017",
      "name": "网宿科技",
      "sector": "股权激励",
      "score": 99,
      "reason": "[股权激励]显著上涨+净流入7.5亿",
      "suggestGroup": "watch"
    },
    {
      "code": "sh600549",
      "name": "厦门钨业",
      "sector": "锂电池",
      "score": 96,
      "reason": "[锂电池]涨停+净流入23.0亿",
      "suggestGroup": "watch"
    },
    {
      "code": "sz002263",
      "name": "大东南",
      "sector": "锂电池",
      "score": 96,
      "reason": "[锂电池]涨停+净流入13.9亿",
      "suggestGroup": "watch"
    },
    {
      "code": "sz002491",
      "name": "通鼎互联",
      "sector": "锂电池",
      "score": 96,
      "reason": "[锂电池]涨停+净流入12.4亿",
      "suggestGroup": "watch"
    },
    {
      "code": "sz002594",
      "name": "比亚迪",
      "sector": "锂电池",
      "score": 96,
      "reason": "[锂电池]净流入10.1亿",
      "suggestGroup": "watch"
    },
    {
      "code": "sz300394",
      "name": "天孚通信",
      "sector": "专精特新",
      "score": 95,
      "reason": "[专精特新]强势拉升+净流入37.7亿",
      "suggestGroup": "watch"
    },
    {
      "code": "sh603799",
      "name": "华友钴业",
      "sector": "锂矿",
      "score": 95,
      "reason": "[锂矿]显著上涨+净流入8.4亿",
      "suggestGroup": "watch"
    },
    {
      "code": "sz300604",
      "name": "长川科技",
      "sector": "专精特新",
      "score": 95,
      "reason": "[专精特新]强势拉升+净流入7.8亿",
      "suggestGroup": "watch"
    }
  ]
}